paig_evaluation/README.md
paig_evaluation/VERSION
paig_evaluation/__init__.py
paig_evaluation/__main__.py
paig_evaluation/command_utils.py
paig_evaluation/config.py
paig_evaluation/constants.py
paig_evaluation/file_utils.py
paig_evaluation/logging_init.py
paig_evaluation/paig_evaluator.py
paig_evaluation/promptfoo_utils.py
paig_evaluation/requirements.txt
paig_evaluation/conf/default_config.yaml
paig_evaluation/conf/security_plugins.json
paig_evaluation-0.0.3.dist-info/METADATA
paig_evaluation-0.0.3.dist-info/WHEEL
paig_evaluation-0.0.3.dist-info/entry_points.txt
paig_evaluation-0.0.3.dist-info/RECORD
