Metadata-Version: 2.4
Name: paig-evaluation
Version: 0.0.3
Summary: PAIG Evaluation
Project-URL: Homepage, https://github.com/privacera/paig
Project-URL: Bug Tracker, https://github.com/privacera/paig/issues
Author-email: Privacera  <support@privacera.com>
License:                                  Apache License
Keywords: Chatbot,Governance,PAIG,PAIG-Evaluation,Privacy,Security
Classifier: License :: Other/Proprietary License
Classifier: Operating System :: OS Independent
Classifier: Programming Language :: Python :: 3
Requires-Python: >=3.10
Requires-Dist: click
Requires-Dist: openai>=1.55.3
Requires-Dist: pyyaml
